kgym/__init__.py
kgym/connectx.py
kgym-0.0.2.dist-info/LICENSE
kgym-0.0.2.dist-info/METADATA
kgym-0.0.2.dist-info/WHEEL
kgym-0.0.2.dist-info/top_level.txt
kgym-0.0.2.dist-info/RECORD
