Metadata-Version: 2.1
Name: kgym
Version: 0.0.2
Summary: Implementations for the OpenAI Gym of Kaggle Environments
Home-page: https://github.com/sebimarkgraf/kgym
Author: Sebastian Markgraf
Author-email: sebastian-markgraf@t-online.de
License: Apache Software License 2.0
Keywords: kgym
Platform: UNKNOWN
Classifier: Development Status :: 2 - Pre-Alpha
Classifier: Intended Audience :: Developers
Classifier: License :: OSI Approved :: Apache Software License
Classifier: Natural Language :: English
Classifier: Programming Language :: Python :: 3
Classifier: Programming Language :: Python :: 3.6
Classifier: Programming Language :: Python :: 3.7
Classifier: Programming Language :: Python :: 3.8
Requires-Python: >=3.5
Requires-Dist: numpy (>=1.0.0)
Requires-Dist: gym (>=0.17.0)
Requires-Dist: kaggle-environments (>=1.0.11)
